pyclimb/__init__.py
pyclimb/converter.py
pyclimb/exceptions.py
pyclimb/grading_system.py
pyclimb/mapper.py
pyclimb-0.2.0.dist-info/LICENSE
pyclimb-0.2.0.dist-info/WHEEL
pyclimb-0.2.0.dist-info/METADATA
pyclimb-0.2.0.dist-info/RECORD
