Metadata-Version: 2.1
Name: pyclimb
Version: 0.2.0
Summary: A library to easily convert climbing route grades between different grading systems.
Home-page: https://pypi.org/project/pyclimb
License: MIT
Keywords: pip,converter,climbing
Author: ilias-ant
Author-email: ilias.antonopoulos@yahoo.gr
Requires-Python: >=3.7,<3.11
Classifier: Development Status :: 3 - Alpha
Classifier: Intended Audience :: Developers
Classifier: Intended Audience :: Other Audience
Classifier: License :: OSI Approved :: MIT License
Classifier: Natural Language :: English
Classifier: Operating System :: OS Independent
Classifier: Programming Language :: Python :: 3
Classifier: Programming Language :: Python :: 3 :: Only
Classifier: Programming Language :: Python :: 3.10
Classifier: Programming Language :: Python :: 3.7
Classifier: Programming Language :: Python :: 3.8
Classifier: Programming Language :: Python :: 3.9
Classifier: Topic :: Software Development :: Libraries :: Python Modules
Project-URL: Repository, https://github.com/ilias-ant/pyclimb
